{
  "header_types" : [
    {
      "name" : "scalars_0",
      "id" : 0,
      "fields" : [
        ["tmp", 32, false]
      ]
    },
    {
      "name" : "standard_metadata",
      "id" : 1,
      "fields" : [
        ["ingress_port", 9, false],
        ["egress_spec", 9, false],
        ["egress_port", 9, false],
        ["instance_type", 32, false],
        ["packet_length", 32, false],
        ["enq_timestamp", 32, false],
        ["enq_qdepth", 19, false],
        ["deq_timedelta", 32, false],
        ["deq_qdepth", 19, false],
        ["ingress_global_timestamp", 48, false],
        ["egress_global_timestamp", 48, false],
        ["mcast_grp", 16, false],
        ["egress_rid", 16, false],
        ["checksum_error", 1, false],
        ["parser_error", 32, false],
        ["priority", 3, false],
        ["_padding", 3, false]
      ]
    },
    {
      "name" : "byte_hdr",
      "id" : 2,
      "fields" : [
        ["value", 8, false]
      ]
    },
    {
      "name" : "variable_length_hdr",
      "id" : 3,
      "fields" : [
        ["content", "*"]
      ],
      "max_length" : 32
    }
  ],
  "headers" : [
    {
      "name" : "scalars",
      "id" : 0,
      "header_type" : "scalars_0",
      "metadata" : true,
      "pi_omit" : true
    },
    {
      "name" : "standard_metadata",
      "id" : 1,
      "header_type" : "standard_metadata",
      "metadata" : true,
      "pi_omit" : true
    },
    {
      "name" : "length",
      "id" : 2,
      "header_type" : "byte_hdr",
      "metadata" : false,
      "pi_omit" : true
    },
    {
      "name" : "field",
      "id" : 3,
      "header_type" : "variable_length_hdr",
      "metadata" : false,
      "pi_omit" : true
    },
    {
      "name" : "test_value",
      "id" : 4,
      "header_type" : "byte_hdr",
      "metadata" : false,
      "pi_omit" : true
    }
  ],
  "header_stacks" : [],
  "header_union_types" : [],
  "header_unions" : [],
  "header_union_stacks" : [],
  "field_lists" : [],
  "errors" : [
    ["NoError", 0],
    ["PacketTooShort", 1],
    ["NoMatch", 2],
    ["StackOutOfBounds", 3],
    ["HeaderTooShort", 4],
    ["ParserTimeout", 5],
    ["ParserInvalidArgument", 6]
  ],
  "enums" : [],
  "parsers" : [
    {
      "name" : "parser",
      "id" : 0,
      "init_state" : "start",
      "parse_states" : [
        {
          "name" : "start",
          "id" : 0,
          "parser_ops" : [
            {
              "parameters" : [
                {
                  "type" : "regular",
                  "value" : "length"
                }
              ],
              "op" : "extract"
            },
            {
              "parameters" : [
                {
                  "type" : "field",
                  "value" : ["scalars", "tmp"]
                },
                {
                  "type" : "expression",
                  "value" : {
                    "type" : "expression",
                    "value" : {
                      "op" : "&",
                      "left" : {
                        "type" : "field",
                        "value" : ["length", "value"]
                      },
                      "right" : {
                        "type" : "hexstr",
                        "value" : "0xffffffff"
                      }
                    }
                  }
                }
              ],
              "op" : "set"
            },
            {
              "parameters" : [
                {
                  "type" : "regular",
                  "value" : "field"
                },
                {
                  "type" : "expression",
                  "value" : {
                    "type" : "field",
                    "value" : ["scalars", "tmp"]
                  }
                }
              ],
              "op" : "extract_VL"
            },
            {
              "parameters" : [
                {
                  "type" : "regular",
                  "value" : "test_value"
                }
              ],
              "op" : "extract"
            }
          ],
          "transitions" : [
            {
              "type" : "hexstr",
              "value" : "0x00",
              "mask" : null,
              "next_state" : "test_zero"
            },
            {
              "value" : "default",
              "mask" : null,
              "next_state" : "test_non_zero"
            }
          ],
          "transition_key" : [
            {
              "type" : "field",
              "value" : ["test_value", "value"]
            }
          ]
        },
        {
          "name" : "test_zero",
          "id" : 1,
          "parser_ops" : [],
          "transitions" : [
            {
              "value" : "default",
              "mask" : null,
              "next_state" : null
            }
          ],
          "transition_key" : []
        },
        {
          "name" : "test_non_zero",
          "id" : 2,
          "parser_ops" : [],
          "transitions" : [
            {
              "value" : "default",
              "mask" : null,
              "next_state" : null
            }
          ],
          "transition_key" : []
        }
      ]
    }
  ],
  "parse_vsets" : [],
  "deparsers" : [
    {
      "name" : "deparser",
      "id" : 0,
      "source_info" : {
        "filename" : "switch-after-varbit.p4",
        "line" : 50,
        "column" : 8,
        "source_fragment" : "deparser"
      },
      "order" : [],
      "primitives" : []
    }
  ],
  "meter_arrays" : [],
  "counter_arrays" : [],
  "register_arrays" : [],
  "calculations" : [],
  "learn_lists" : [],
  "actions" : [
    {
      "name" : "switchaftervarbit55",
      "id" : 0,
      "runtime_data" : [],
      "primitives" : [
        {
          "op" : "assign",
          "parameters" : [
            {
              "type" : "field",
              "value" : ["length", "value"]
            },
            {
              "type" : "hexstr",
              "value" : "0x00"
            }
          ],
          "source_info" : {
            "filename" : "switch-after-varbit.p4",
            "line" : 55,
            "column" : 8,
            "source_fragment" : "h.length.value = 0"
          }
        }
      ]
    }
  ],
  "pipelines" : [
    {
      "name" : "ingress",
      "id" : 0,
      "source_info" : {
        "filename" : "switch-after-varbit.p4",
        "line" : 51,
        "column" : 8,
        "source_fragment" : "ingress"
      },
      "init_table" : "tbl_switchaftervarbit55",
      "tables" : [
        {
          "name" : "tbl_switchaftervarbit55",
          "id" : 0,
          "source_info" : {
            "filename" : "switch-after-varbit.p4",
            "line" : 55,
            "column" : 23,
            "source_fragment" : "="
          },
          "key" : [],
          "match_type" : "exact",
          "type" : "simple",
          "max_size" : 1024,
          "with_counters" : false,
          "support_timeout" : false,
          "direct_meters" : null,
          "action_ids" : [0],
          "actions" : ["switchaftervarbit55"],
          "base_default_next" : null,
          "next_tables" : {
            "switchaftervarbit55" : null
          },
          "default_entry" : {
            "action_id" : 0,
            "action_const" : true,
            "action_data" : [],
            "action_entry_const" : true
          }
        }
      ],
      "action_profiles" : [],
      "conditionals" : []
    },
    {
      "name" : "egress",
      "id" : 1,
      "source_info" : {
        "filename" : "switch-after-varbit.p4",
        "line" : 48,
        "column" : 8,
        "source_fragment" : "egress"
      },
      "init_table" : null,
      "tables" : [],
      "action_profiles" : [],
      "conditionals" : []
    }
  ],
  "checksums" : [],
  "force_arith" : [],
  "extern_instances" : [],
  "field_aliases" : [
    [
      "queueing_metadata.enq_timestamp",
      ["standard_metadata", "enq_timestamp"]
    ],
    [
      "queueing_metadata.enq_qdepth",
      ["standard_metadata", "enq_qdepth"]
    ],
    [
      "queueing_metadata.deq_timedelta",
      ["standard_metadata", "deq_timedelta"]
    ],
    [
      "queueing_metadata.deq_qdepth",
      ["standard_metadata", "deq_qdepth"]
    ],
    [
      "intrinsic_metadata.ingress_global_timestamp",
      ["standard_metadata", "ingress_global_timestamp"]
    ],
    [
      "intrinsic_metadata.egress_global_timestamp",
      ["standard_metadata", "egress_global_timestamp"]
    ],
    [
      "intrinsic_metadata.mcast_grp",
      ["standard_metadata", "mcast_grp"]
    ],
    [
      "intrinsic_metadata.egress_rid",
      ["standard_metadata", "egress_rid"]
    ],
    [
      "intrinsic_metadata.priority",
      ["standard_metadata", "priority"]
    ]
  ],
  "program" : "./switch-after-varbit.p4i",
  "__meta__" : {
    "version" : [2, 18],
    "compiler" : "https://github.com/p4lang/p4c"
  }
}

